Metadata-Version: 2.1
Name: quaver.py
Version: 0.2.3
Summary: A Python wrapper for the Quaver API
Home-page: https://github.com/SELECT-stupidity-FROM-discord/quaver.py
Author: SELECT-stupidity-FROM-discord
License: MIT
Project-URL: Issue tracker, https://github.com/SELECT-stupidity-FROM-discord/quaver.py/issues
Platform: UNKNOWN
Classifier: Development Status :: 5 - Production/Stable
Classifier: License :: OSI Approved :: MIT License
Classifier: Intended Audience :: Developers
Classifier: Natural Language :: English
Classifier: Operating System :: OS Independent
Classifier: Programming Language :: Python :: 3.8
Classifier: Programming Language :: Python :: 3.9
Classifier: Programming Language :: Python :: 3.10
Classifier: Topic :: Internet
Classifier: Topic :: Software Development :: Libraries
Classifier: Topic :: Software Development :: Libraries :: Python Modules
Classifier: Topic :: Utilities
Classifier: Typing :: Typed
Requires-Python: >=3.8.0
License-File: LICENSE
